NiukeDichanXingyeQiuzhiGonglveWankePian20212022Fix1/README.md
NiukeDichanXingyeQiuzhiGonglveWankePian20212022Fix1/__init__.py
NiukeDichanXingyeQiuzhiGonglveWankePian20212022Fix1/__main__.py
NiukeDichanXingyeQiuzhiGonglveWankePian20212022Fix1/file.epub
NiukeDichanXingyeQiuzhiGonglveWankePian20212022Fix1/index.html
NiukeDichanXingyeQiuzhiGonglveWankePian20212022Fix1/css/__init__.py
NiukeDichanXingyeQiuzhiGonglveWankePian20212022Fix1/css/annotations.css
NiukeDichanXingyeQiuzhiGonglveWankePian20212022Fix1/css/main.css
NiukeDichanXingyeQiuzhiGonglveWankePian20212022Fix1/css/normalize.css
NiukeDichanXingyeQiuzhiGonglveWankePian20212022Fix1/css/popup.css
NiukeDichanXingyeQiuzhiGonglveWankePian20212022Fix1/font/__init__.py
NiukeDichanXingyeQiuzhiGonglveWankePian20212022Fix1/font/fontello.eot
NiukeDichanXingyeQiuzhiGonglveWankePian20212022Fix1/font/fontello.svg
NiukeDichanXingyeQiuzhiGonglveWankePian20212022Fix1/font/fontello.ttf
NiukeDichanXingyeQiuzhiGonglveWankePian20212022Fix1/font/fontello.woff
NiukeDichanXingyeQiuzhiGonglveWankePian20212022Fix1/img/__init__.py
NiukeDichanXingyeQiuzhiGonglveWankePian20212022Fix1/img/annotator-glyph-sprite.png
NiukeDichanXingyeQiuzhiGonglveWankePian20212022Fix1/img/annotator-icon-sprite.png
NiukeDichanXingyeQiuzhiGonglveWankePian20212022Fix1/img/apple-touch-icon.png
NiukeDichanXingyeQiuzhiGonglveWankePian20212022Fix1/img/cancelfullscreen.png
NiukeDichanXingyeQiuzhiGonglveWankePian20212022Fix1/img/close.png
NiukeDichanXingyeQiuzhiGonglveWankePian20212022Fix1/img/fullscreen.png
NiukeDichanXingyeQiuzhiGonglveWankePian20212022Fix1/img/loader.gif
NiukeDichanXingyeQiuzhiGonglveWankePian20212022Fix1/img/menu-icon.png
NiukeDichanXingyeQiuzhiGonglveWankePian20212022Fix1/img/save.png
NiukeDichanXingyeQiuzhiGonglveWankePian20212022Fix1/img/saved.png
NiukeDichanXingyeQiuzhiGonglveWankePian20212022Fix1/img/settings-s.png
NiukeDichanXingyeQiuzhiGonglveWankePian20212022Fix1/img/settings.png
niuke_dichan_xingye_qiuzhi_gonglve_wanke_pian_2021_2022_fix1-2025.3.25.1.dist-info/METADATA
niuke_dichan_xingye_qiuzhi_gonglve_wanke_pian_2021_2022_fix1-2025.3.25.1.dist-info/WHEEL
niuke_dichan_xingye_qiuzhi_gonglve_wanke_pian_2021_2022_fix1-2025.3.25.1.dist-info/entry_points.txt
niuke_dichan_xingye_qiuzhi_gonglve_wanke_pian_2021_2022_fix1-2025.3.25.1.dist-info/top_level.txt
niuke_dichan_xingye_qiuzhi_gonglve_wanke_pian_2021_2022_fix1-2025.3.25.1.dist-info/RECORD
